umapjax/__init__.py
umapjax/_core.py
umapjax/layouts/__init__.py
umapjax/layouts/jax.py
umapjax/layouts/mlx.py
umapjax/layouts/torch.py
umapjax/spectral/__init__.py
umapjax/spectral/jax.py
umapjax/spectral/torch.py
umapjax-0.1.0.dist-info/METADATA
umapjax-0.1.0.dist-info/WHEEL
umapjax-0.1.0.dist-info/licenses/LICENSE
umapjax-0.1.0.dist-info/RECORD
