Metadata-Version: 2.4
Name: umapjax
Version: 0.1.0
Summary: UMAP, but optimized with jax.
Project-URL: Homepage, https://github.com/adamgayoso/umapjax
Project-URL: Source, https://github.com/adamgayoso/umapjax
Author: Adam Gayoso
Maintainer-email: Adam Gayoso <adamgayoso@gmail.com>
License: BSD 3-Clause License
License-File: LICENSE
Classifier: Programming Language :: Python :: 3 :: Only
Classifier: Programming Language :: Python :: 3.11
Classifier: Programming Language :: Python :: 3.12
Classifier: Programming Language :: Python :: 3.13
Classifier: Programming Language :: Python :: 3.14
Requires-Python: >=3.11
Requires-Dist: chex
Requires-Dist: jaxtyping
Requires-Dist: mlx[cpu]>=0.30.4
Requires-Dist: umap-learn
